bass_model/__init__.py
bass_model/bass_model.py
bass_model-0.1.0.dist-info/AUTHORS.rst
bass_model-0.1.0.dist-info/METADATA
bass_model-0.1.0.dist-info/WHEEL
bass_model-0.1.0.dist-info/top_level.txt
bass_model-0.1.0.dist-info/RECORD
