Metadata-Version: 2.1
Name: bass-model
Version: 0.1.0
Summary: Bass-Model package for Marketing Analytics
Home-page: https://github.com/lyov9999/bass_model
Author: Levon Yesayan
Author-email: levon_yesayan@edu.aua.am
Keywords: bass_model
Classifier: Development Status :: 2 - Pre-Alpha
Classifier: Intended Audience :: Developers
Classifier: Natural Language :: English
Classifier: Programming Language :: Python :: 3
Classifier: Programming Language :: Python :: 3.6
Classifier: Programming Language :: Python :: 3.7
Classifier: Programming Language :: Python :: 3.8
Requires-Python: >=3.6
License-File: AUTHORS.rst
